ovos_tts_plugin_server/__init__.py
ovos_tts_plugin_server/version.py
ovos_tts_plugin_server-0.0.4.dist-info/LICENSE
ovos_tts_plugin_server-0.0.4.dist-info/METADATA
ovos_tts_plugin_server-0.0.4.dist-info/WHEEL
ovos_tts_plugin_server-0.0.4.dist-info/entry_points.txt
ovos_tts_plugin_server-0.0.4.dist-info/top_level.txt
ovos_tts_plugin_server-0.0.4.dist-info/zip-safe
ovos_tts_plugin_server-0.0.4.dist-info/RECORD
