Metadata-Version: 2.1
Name: ovos-tts-plugin-server
Version: 0.0.4
Summary: ovos tts server plugin for mycroft
Home-page: https://github.com/OpenVoiceOS/ovos-tts-server-plugin
Author: JarbasAi
Author-email: jarbasai@mailfence.com
License: Apache-2.0
Keywords: mycroft OpenVoiceOS OVOS plugin tts
Classifier: Development Status :: 3 - Alpha
Classifier: Intended Audience :: Developers
Classifier: Topic :: Text Processing :: Linguistic
Classifier: License :: OSI Approved :: Apache Software License
Classifier: Programming Language :: Python :: 3.8
Classifier: Programming Language :: Python :: 3.9
Classifier: Programming Language :: Python :: 3.10
Classifier: Programming Language :: Python :: 3.11
Classifier: Programming Language :: Python :: 3.12
License-File: LICENSE
Requires-Dist: ovos-plugin-manager<2.0.0,>=1.0.0
Requires-Dist: requests
